Metadata-Version: 2.1
Name: consolebar
Version: 1.2
Summary: Stunning progress bars for consoles for showing progress of python loops!
Home-page: https://github.com/AbhayTr/ConsoleBar
Author: Abhay Tripathi
Author-email: abhay.triipathi@gmail.com
License: MIT
Download-URL: https://github.com/AbhayTr/ConsoleBar/archive/v1.2.tar.gz
Keywords: Console,Progress Bar,Python Progress Bar,Console Progress Bar
Platform: UNKNOWN
Classifier: Development Status :: 5 - Production/Stable
Classifier: Intended Audience :: Developers
Classifier: Topic :: Software Development :: Build Tools
Classifier: License :: OSI Approved :: MIT License
Classifier: Programming Language :: Python :: 2
Classifier: Programming Language :: Python :: 3
Classifier: Programming Language :: Python :: 3.4
Classifier: Programming Language :: Python :: 3.5
Classifier: Programming Language :: Python :: 3.6
